grill/names/__init__.py
grill/tokens/ids/CGAsset.cfg
grill/tokens/ids/LifeTR.cfg
grill/tokens/ids/__init__.py
grill_names-2.6.2.dist-info/LICENSE
grill_names-2.6.2.dist-info/METADATA
grill_names-2.6.2.dist-info/WHEEL
grill_names-2.6.2.dist-info/top_level.txt
grill_names-2.6.2.dist-info/RECORD
