Metadata-Version: 2.1
Name: grill-names
Version: 2.6.2
Summary: Name objects for digital content creation.
Home-page: https://github.com/thegrill/grill-names
Author: Christian López Barrón
Author-email: chris.gfz@gmail.com
Keywords: naming convention cg
Classifier: Programming Language :: Python :: 3.8
Classifier: Programming Language :: Python :: 3.9
Classifier: Programming Language :: Python :: 3.10
Classifier: Programming Language :: Python :: 3.11
Classifier: Programming Language :: Python :: 3.12
Classifier: Programming Language :: Python :: 3.13
License-File: LICENSE
Requires-Dist: naming>=0.6
Provides-Extra: docs
Requires-Dist: sphinx; extra == "docs"
Requires-Dist: myst-parser; extra == "docs"
Requires-Dist: sphinx-toggleprompt; extra == "docs"
Requires-Dist: sphinx-copybutton; extra == "docs"
Requires-Dist: sphinx-togglebutton; extra == "docs"
Requires-Dist: sphinx-hoverxref; extra == "docs"
Requires-Dist: shibuya; extra == "docs"
